duauto/__init__.py
duauto/action_mapping.py
duauto/actions.py
duauto/assertions.py
duauto/locator_mapping.py
duauto/web_driver_manager.py
duauto-1.0.3.dist-info/METADATA
duauto-1.0.3.dist-info/WHEEL
duauto-1.0.3.dist-info/top_level.txt
duauto-1.0.3.dist-info/RECORD
