Metadata-Version: 2.2
Name: duauto
Version: 1.0.3
Requires-Dist: attrs==24.2.0
Requires-Dist: certifi==2024.8.30
Requires-Dist: cffi==1.17.1
Requires-Dist: charset-normalizer==3.3.2
Requires-Dist: colorama==0.4.6
Requires-Dist: coverage==7.6.1
Requires-Dist: docutils==0.21.2
Requires-Dist: h11==0.14.0
Requires-Dist: idna==3.10
Requires-Dist: importlib_metadata==8.5.0
Requires-Dist: iniconfig==2.0.0
Requires-Dist: jaraco.classes==3.4.0
Requires-Dist: jaraco.context==6.0.1
Requires-Dist: jaraco.functools==4.1.0
Requires-Dist: Jinja2==3.1.4
Requires-Dist: keyring==25.4.1
Requires-Dist: markdown-it-py==3.0.0
Requires-Dist: MarkupSafe==2.1.5
Requires-Dist: mdurl==0.1.2
Requires-Dist: more-itertools==10.5.0
Requires-Dist: nh3==0.2.18
Requires-Dist: outcome==1.3.0.post0
Requires-Dist: packaging==24.1
Requires-Dist: pkginfo==1.10.0
Requires-Dist: pluggy==1.5.0
Requires-Dist: pycparser==2.22
Requires-Dist: Pygments==2.18.0
Requires-Dist: PySocks==1.7.1
Requires-Dist: pytest==8.3.3
Requires-Dist: pytest-cov==5.0.0
Requires-Dist: pytest-html==4.1.1
Requires-Dist: pytest-metadata==3.1.1
Requires-Dist: pywin32-ctypes==0.2.3
Requires-Dist: readme_renderer==44.0
Requires-Dist: requests==2.32.3
Requires-Dist: requests-toolbelt==1.0.0
Requires-Dist: rfc3986==2.0.0
Requires-Dist: rich==13.8.1
Requires-Dist: selenium==4.25.0
Requires-Dist: setuptools==75.1.0
Requires-Dist: sniffio==1.3.1
Requires-Dist: sortedcontainers==2.4.0
Requires-Dist: trio==0.26.2
Requires-Dist: trio-websocket==0.11.1
Requires-Dist: twine==5.1.1
Requires-Dist: typing_extensions==4.12.2
Requires-Dist: urllib3==2.2.3
Requires-Dist: websocket-client==1.8.0
Requires-Dist: wheel==0.44.0
Requires-Dist: wsproto==1.2.0
Requires-Dist: zipp==3.20.2
Dynamic: requires-dist
